pkg_version_mgr/__init__.py
pkg_version_mgr/version.py
pkg_version_mgr-1.0.4.dist-info/LICENSE
pkg_version_mgr-1.0.4.dist-info/METADATA
pkg_version_mgr-1.0.4.dist-info/WHEEL
pkg_version_mgr-1.0.4.dist-info/top_level.txt
pkg_version_mgr-1.0.4.dist-info/RECORD
