Metadata-Version: 2.1
Name: pkg-version-mgr
Version: 1.0.4
Summary: Helper for managing Python package versions
Home-page: http://www.lumince.co
Author: Curtis Forrester
License: MIT
Keywords: gitlab tools
Platform: UNKNOWN
Classifier: Development Status :: 3 - Alpha
Classifier: Environment :: Console
Classifier: Intended Audience :: Developers
Classifier: License :: OSI Approved :: MIT License
Classifier: Programming Language :: Python
Classifier: Programming Language :: Python :: 2
Classifier: Programming Language :: Python :: 2.7
Classifier: Programming Language :: Python :: 3
Classifier: Programming Language :: Python :: 3.7
Classifier: Topic :: Software Development :: Libraries
Requires-Python: >=2.7
Requires-Dist: future
